{
    "shoes": {
        "items": [
            {
                "id": 1,
                "name": "VANS OG AUTHENTIC LX",
                "price": 379,
                "currency": "RON",
                "image": "https://i.imgur.com/D7R4OiR.jpg",
                "size": 45,
                "colour": "Blue",
                "material": "SUEDE/ CANVAS",
                "brand": "Vans",
                "description": "Vans Authentic shoes were first manufactured in 1966. They were designed by Paul Van Doren, founder of the company, and today they are extremely popular in skateboarding culture. The Vans Authentic Women's range are available in a variety of different patterns and colourways."
            },
            {
                "id": 2,
                "name": "VANS OG STYLE 138 LX",
                "price": 368,
                "currency": "RON",
                "image": "https://i.imgur.com/U6mHZTD.jpg",
                "size": 45,
                "colour": "Marshmallow/ Multi",
                "material": "SUEDE/CANVAS",
                "brand": "Vans",
                "description": "The Vans Style 138 sneakers are a re-introduced model of one of the most legendary Vans silhouettes. Check them out at Footshop."
            },
            {
                "id": 3,
                "name": "ADIDAS U_PATH X W",
                "price": 250,
                "currency": "RON",
                "image": "https://i.imgur.com/gEwR4OU.jpg",
                "size": 45,
                "colour": "Black",
                "material": "Canvas",
                "brand": "Adidas",
                "description": "Upper - Textile ▩ - is a lightweight material, which is offered in a very wide color scale and is mainly used for summer footwear."
            }
        ],
        "image": "https://i.imgur.com/jAjHaio.jpg",
        "name": "Sneakers",
        "description": "Walk with confidence!"
    },
    "hoodies": {
        "items": [
            {
                "id": 4,
                "name": "CHAMPION HOODIE",
                "price": 155,
                "currency": "RON",
                "image": "https://i.imgur.com/XBx2woD.jpg",
                "size": "L",
                "colour": "Black",
                "material": "French Terrys",
                "brand": "Champion",
                "description": "Composition - 100% Cotton - A very soft and pleasant material whose properties include tensile strength and elongation at break. Unlike other materials, it does not get damaged easily when washed often."
            },
            {
                "id": 5,
                "name": "ADIDAS HOODIE",
                "price": 200,
                "currency": "RON",
                "image": "https://i.imgur.com/vRPeNBR.jpg",
                "size": "L",
                "colour": "Green",
                "material": "French Terry",
                "brand": "Adidas",
                "description": "Just a little something extra. Sometimes that's all you need, and this adidas hoodie delivers with ruffles popping off the sleeves. Soft French terry means that wherever you are, you can really relax in total comfort. Because when you feel good, you look good. So throw on this sweatshirt and do both.."
            },
            {
                "id": 6,
                "name": "VANS 66 SUPPLY HOODIE",
                "price": 205,
                "currency": "RON",
                "image": "https://i.imgur.com/X3nkPUT.jpg",
                "size": "L",
                "colour": "Multicolor",
                "material": "Polyester/Cotton",
                "brand": "Vans",
                "description": "76% Cotton - A very soft and pleasant material whose properties include tensile strength and elongation at break. Unlike other materials, it does not get damaged easily when washed often.24% Polyester - a very strong synthetic fiber that boasts high heat resistance and excellent odor absorption"
            },
            {
                "id": 7,
                "name": "FILA TAVORA HOODIE",
                "price": 137,
                "currency": "RON",
                "image": "https://i.imgur.com/OCarRYG.jpg",
                "size": "L",
                "colour": "Pastel Pink",
                "material": "French Terry   ",
                "brand": "FILA",
                "description": "65% Cotton - A very soft and pleasant material whose properties include tensile strength and elongation at break. Unlike other materials, it does not get damaged easily when washed often.35% Polyester - a very strong synthetic fiber that boasts high heat resistance and excellent odor absorption"
            }
        ],
        "image": "https://i.imgur.com/OSPrtKM.jpg",
        "name": "Hoodies",
        "description": "Get ready for the Sweater Weather!"
    },
    "pants": {
        "items": [
            {
                "id": 8,
                "name": "HOPE KRISSY TROUSERS",
                "price": 120,
                "currency": "RON",
                "image": "https://i.imgur.com/7oGFyy7.jpg",
                "size": "34",
                "colour": "Gray",
                "material": "Viscose",
                "brand": "Hope",
                "description": "Composition - Viscose - the look is similar to cotton and is equally comfortable to touch, but the cotton is different with its better heat conducting properties."
            },
            {
                "id": 9,
                "name": "SELECTED CROPPED TROUSERS",
                "price": 40,
                "currency": "RON",
                "image": "https://i.imgur.com/dHipIHi.jpg",
                "size": "34",
                "colour": "Black",
                "material": "Visocose, Elastane, Polyester",
                "brand": "Selected",
                "description": "32% Viscose - the look is similar to cotton and is equally comfortable to touch, but the cotton is different with its better heat conducting properties.4% Elastane - used in combination with other materials, especially for its excellent flexibility - its fiber can stretch up to three times its normal length and then return to its original state.64% Polyester - a very strong synthetic fiber that boasts high heat resistance and excellent odor absorption"
            }
        ],
        "image": "https://i.imgur.com/B3KqcfD.jpg",
        "name": "Pants/Jeans",
        "description": "Steal that Steve Jobs or Mark Zuckerberg look!"
    },
    "jackets": {
        "items": [
            {
                "id": 10,
                "name": "HELLY HANSEN W ARYA PARKA",
                "price": 600,
                "currency": "RON",
                "image": "https://i.imgur.com/GJqYSja.jpg",
                "size": "L",
                "colour": "Khaki green",
                "material": "Polyester",
                "brand": "Helly Hansen",
                "description": "Outer material - 100% Polyester, Filling material - 100% Polyester"
            },
            {
                "id": 11,
                "name": "ADIDAS MYSHELTER COLD RDY",
                "price": 800,
                "currency": "RON",
                "image": "https://i.imgur.com/qlULhTP.jpg",
                "size": "L",
                "colour": "Black",
                "material": "Polyester",
                "brand": "Adidas",
                "description": "Whether you're grabbing food in Chinatown or bar hopping in Brooklyn, the last thing you want to worry about is getting cold. Enter the MYSHELTER COLD.RDY Parka. The adidas insulating technology of overlapping sections of HyperDRY™ Down keep the warmth in and the cold out. Internal carry straps for when you head indoors, weatherproof vest for when you've got no option but to hit the streets."
            }
        ],
        "image": "https://i.imgur.com/bvF2ycr.jpg",
        "name": "Outerwear",
        "description": "Keep yourself warm during cold times!"
    },
    "tshirts": {
        "items": [
            {
                "id": 12,
                "name": "ADIDAS CAMO TONGUE TEE",
                "price": 105,
                "currency": "RON",
                "image": "https://i.imgur.com/BaAcViE.jpg",
                "size": "L",
                "colour": "White Camo",
                "material": "Cotton",
                "brand": "Adidas",
                "description": "Composition - 100% Cotton - A very soft and pleasant material whose properties include tensile strength and elongation at break. Unlike other materials, it does not get damaged easily when washed often."
            },
            {
                "id": 13,
                "name": "NIKE SPORTSWEAR TEE",
                "price": 99,
                "currency": "RON",
                "image": "https://i.imgur.com/EGnMqXO.jpg",
                "size": "L",
                "colour": "White",
                "material": "Cotton",
                "brand": "Nike",
                "description": "Composition - 100% Cotton - A very soft and pleasant material whose properties include tensile strength and elongation at break. Unlike other materials, it does not get damaged easily when washed often."
            },
            {
                "id": 14,
                "name": "THE NORTH FACE RAG BOX TEE",
                "price": 205,
                "currency": "RON",
                "image": "https://i.imgur.com/O7UtGt4.jpg",
                "size": "L",
                "colour": "Mineral Gray",
                "material": "Cotton",
                "brand": "Vans",
                "description": "Composition - 100% Cotton - A very soft and pleasant material whose properties include tensile strength and elongation at break. Unlike other materials, it does not get damaged easily when washed often."
            }
        ],
        "image": "https://i.imgur.com/92X7IIj.png",
        "name": "T-Shirts",
        "description": "Get you essentials on point!"
    },
    "accesories": {
        "items": [
            {
                "id": 15,
                "name": "ADIDAS SOLID CREW SOCK 3-PACK",
                "price": 85,
                "currency": "RON",
                "image": "https://i.imgur.com/n1U3UtU.jpg",
                "size": "Universal",
                "colour": "Cotton",
                "material": "Cashmere",
                "brand": "Adidas",
                "description": "Crew, 3-pack elite socks made of cotton."
            },
            {
                "id": 16,
                "name": "ADIDAS SPORT MODULAR BACKPACK",
                "price": 200,
                "currency": "RON",
                "image": "https://i.imgur.com/gGHTNHn.jpg",
                "size": "L",
                "colour": "Khaki green/white",
                "material": "Polyester",
                "brand": "Adidas",
                "description": "Backpack from Adidas made from recycled polyester"
            }
        ],
        "image": "https://i.imgur.com/bQBGmjX.jpg",
        "name": "Accessories",
        "description": "Every random thing your heart desires!"
    }
}